setup.cfg
setup.py
pyetherscan/__init__.py
pyetherscan/tokens.py
python_etherscan_api.egg-info/PKG-INFO
python_etherscan_api.egg-info/SOURCES.txt
python_etherscan_api.egg-info/dependency_links.txt
python_etherscan_api.egg-info/requires.txt
python_etherscan_api.egg-info/top_level.txt
python_etherscan_api.egg-info/zip-safe