Metadata-Version: 1.0
Name: python-etherscan-api
Version: 0.0.3
Summary: Python API for interacting with etherscan.io.
Home-page: https://github.com/nkgilley/python-etherscan-api
Author: Nolan Gilley
Author-email: nkgilley@gmail.com
License: MIT
Platform: UNKNOWN
